aspenautokit/__init__.py
aspenautokit/aspen_connection.py
aspenautokit/close_aspen.py
aspenautokit/excel_connection.py
aspenautokit/get_path.py
aspenautokit/main.py
aspenautokit/save_results.py
aspenautokit/test.py
aspenautokit-0.1.2.dist-info/licenses/license.txt
aspenautokit-0.1.2.dist-info/METADATA
aspenautokit-0.1.2.dist-info/WHEEL
aspenautokit-0.1.2.dist-info/entry_points.txt
aspenautokit-0.1.2.dist-info/top_level.txt
aspenautokit-0.1.2.dist-info/RECORD
