Metadata-Version: 2.4
Name: aspenautokit
Version: 0.1.2
Summary: A Python package for automating Aspen Plus simulations
Author: Vincent Bailey Ladd
Maintainer: Vincent Bailey Ladd
License-Expression: GPL-2.0-only
Project-URL: Homepage, https://github.com/BaileyLadd01/AspenAutoKit
Project-URL: Repository, https://github.com/BaileyLadd01/AspenAutoKit
Keywords: aspen,simulation,automation,chemical engineering,process simulation
Classifier: Development Status :: 3 - Alpha
Classifier: Intended Audience :: Science/Research
Classifier: Operating System :: Microsoft :: Windows
Classifier: Programming Language :: Python :: 3
Classifier: Programming Language :: Python :: 3.8
Classifier: Programming Language :: Python :: 3.9
Classifier: Programming Language :: Python :: 3.10
Classifier: Programming Language :: Python :: 3.11
Classifier: Topic :: Scientific/Engineering :: Chemistry
Classifier: Topic :: Scientific/Engineering :: Physics
Requires-Python: >=3.8
License-File: license.txt
Requires-Dist: pandas
Requires-Dist: numpy
Requires-Dist: joblib
Requires-Dist: openpyxl
Provides-Extra: dev
Requires-Dist: pytest>=6.0; extra == "dev"
Requires-Dist: pytest-cov>=2.0; extra == "dev"
Requires-Dist: black>=22.0; extra == "dev"
Requires-Dist: flake8>=4.0; extra == "dev"
Requires-Dist: mypy>=0.950; extra == "dev"
Provides-Extra: windows
Requires-Dist: pywin32>=305; extra == "windows"
Dynamic: license-file
